{
  "font": "GF_ofl_mashanzheng_MaShanZheng-Regular",
  "chars": [
    "容",
    "器",
    "挖",
    "州"
  ],
  "num_ref_sets": 4,
  "sample_steps": 20,
  "results": {
    "60k": {
      "容": {
        "ref_chars": [
          [
            "阳",
            "侧",
            "允",
            "潘",
            "型",
            "赋",
            "下",
            "土"
          ],
          [
            "嘀",
            "氯",
            "眉",
            "誉",
            "歧",
            "啡",
            "纤",
            "锨"
          ],
          [
            "瞄",
            "毡",
            "轩",
            "阱",
            "四",
            "廓",
            "镰",
            "翘"
          ],
          [
            "华",
            "碟",
            "尖",
            "唧",
            "熊",
            "苛",
            "轨",
            "恋"
          ]
        ],
        "pair_l1_mean": 0.2974760830402374,
        "pair_l1_max": 0.3732363283634186,
        "pair_mse_mean": 0.5182533065478007,
        "target_l1_mean": 0.2559388019144535,
        "target_l1_std": 0.04446747526526451
      },
      "器": {
        "ref_chars": [
          [
            "吃",
            "盯",
            "佃",
            "下",
            "狡",
            "骨",
            "氏",
            "晌"
          ],
          [
            "君",
            "困",
            "卧",
            "爸",
            "码",
            "侣",
            "平",
            "沿"
          ],
          [
            "哩",
            "登",
            "欧",
            "测",
            "枯",
            "累",
            "仆",
            "尘"
          ],
          [
            "飒",
            "邓",
            "串",
            "黄",
            "谱",
            "隔",
            "火",
            "冷"
          ]
        ],
        "pair_l1_mean": 0.4204362283150355,
        "pair_l1_max": 0.4613097608089447,
        "pair_mse_mean": 0.755191574494044,
        "target_l1_mean": 0.42571473866701126,
        "target_l1_std": 0.04827306792140007
      },
      "挖": {
        "ref_chars": [
          [
            "嘀",
            "愿",
            "蔓",
            "荔",
            "浴",
            "夕",
            "瓢",
            "癌"
          ],
          [
            "儿",
            "遍",
            "蔗",
            "险",
            "默",
            "示",
            "签",
            "里"
          ],
          [
            "穴",
            "杰",
            "市",
            "眶",
            "黔",
            "浴",
            "光",
            "什"
          ],
          [
            "疆",
            "贾",
            "帽",
            "鸵",
            "包",
            "默",
            "慰",
            "偶"
          ]
        ],
        "pair_l1_mean": 0.33503657082716626,
        "pair_l1_max": 0.414993554353714,
        "pair_mse_mean": 0.5894675453503927,
        "target_l1_mean": 0.32889407128095627,
        "target_l1_std": 0.06298403441905975
      },
      "州": {
        "ref_chars": [
          [
            "酗",
            "尔",
            "卢",
            "柠",
            "吆",
            "号",
            "哪",
            "咕"
          ],
          [
            "个",
            "哗",
            "点",
            "命",
            "扣",
            "岖",
            "泛",
            "口"
          ],
          [
            "爪",
            "血",
            "徊",
            "趴",
            "泛",
            "苞",
            "笆",
            "昏"
          ],
          [
            "节",
            "迅",
            "彰",
            "赋",
            "玉",
            "晶",
            "癌",
            "曼"
          ]
        ],
        "pair_l1_mean": 0.37027959028879803,
        "pair_l1_max": 0.4886476993560791,
        "pair_mse_mean": 0.6705402284860611,
        "target_l1_mean": 0.315134733915329,
        "target_l1_std": 0.07286842912435532
      }
    },
    "90k": {
      "容": {
        "ref_chars": [
          [
            "阳",
            "侧",
            "允",
            "潘",
            "型",
            "赋",
            "下",
            "土"
          ],
          [
            "嘀",
            "氯",
            "眉",
            "誉",
            "歧",
            "啡",
            "纤",
            "锨"
          ],
          [
            "瞄",
            "毡",
            "轩",
            "阱",
            "四",
            "廓",
            "镰",
            "翘"
          ],
          [
            "华",
            "碟",
            "尖",
            "唧",
            "熊",
            "苛",
            "轨",
            "恋"
          ]
        ],
        "pair_l1_mean": 0.32071298360824585,
        "pair_l1_max": 0.3614111542701721,
        "pair_mse_mean": 0.5652733544508616,
        "target_l1_mean": 0.2510206252336502,
        "target_l1_std": 0.03953611105680466
      },
      "器": {
        "ref_chars": [
          [
            "吃",
            "盯",
            "佃",
            "下",
            "狡",
            "骨",
            "氏",
            "晌"
          ],
          [
            "君",
            "困",
            "卧",
            "爸",
            "码",
            "侣",
            "平",
            "沿"
          ],
          [
            "哩",
            "登",
            "欧",
            "测",
            "枯",
            "累",
            "仆",
            "尘"
          ],
          [
            "飒",
            "邓",
            "串",
            "黄",
            "谱",
            "隔",
            "火",
            "冷"
          ]
        ],
        "pair_l1_mean": 0.4375697275002797,
        "pair_l1_max": 0.5086145401000977,
        "pair_mse_mean": 0.784973531961441,
        "target_l1_mean": 0.4618396759033203,
        "target_l1_std": 0.039952315390110016
      },
      "挖": {
        "ref_chars": [
          [
            "嘀",
            "愿",
            "蔓",
            "荔",
            "浴",
            "夕",
            "瓢",
            "癌"
          ],
          [
            "儿",
            "遍",
            "蔗",
            "险",
            "默",
            "示",
            "签",
            "里"
          ],
          [
            "穴",
            "杰",
            "市",
            "眶",
            "黔",
            "浴",
            "光",
            "什"
          ],
          [
            "疆",
            "贾",
            "帽",
            "鸵",
            "包",
            "默",
            "慰",
            "偶"
          ]
        ],
        "pair_l1_mean": 0.32625195880730945,
        "pair_l1_max": 0.3798338770866394,
        "pair_mse_mean": 0.5727289319038391,
        "target_l1_mean": 0.3202717751264572,
        "target_l1_std": 0.07384984940290451
      },
      "州": {
        "ref_chars": [
          [
            "酗",
            "尔",
            "卢",
            "柠",
            "吆",
            "号",
            "哪",
            "咕"
          ],
          [
            "个",
            "哗",
            "点",
            "命",
            "扣",
            "岖",
            "泛",
            "口"
          ],
          [
            "爪",
            "血",
            "徊",
            "趴",
            "泛",
            "苞",
            "笆",
            "昏"
          ],
          [
            "节",
            "迅",
            "彰",
            "赋",
            "玉",
            "晶",
            "癌",
            "曼"
          ]
        ],
        "pair_l1_mean": 0.3309145172437032,
        "pair_l1_max": 0.4866359829902649,
        "pair_mse_mean": 0.5968959331512451,
        "target_l1_mean": 0.3020714819431305,
        "target_l1_std": 0.06776124238967896
      }
    }
  }
}